secflash/__init__.py
secflash/config.py
secflash/database.py
secflash/logger.py
secflash/nvd_client.py
secflash/report_generator.py
secflash/vulnerability_analyzer.py
secflash/resources/logo.png
secflash/resources/fonts/DejaVuSans-Bold.ttf
secflash/resources/fonts/DejaVuSans.ttf
tests/__init__.py
tests/test_database.py
tests/test_nvd_client.py
tests/test_vulnerability_analyzer.py
secflash-0.1.2.dist-info/METADATA
secflash-0.1.2.dist-info/WHEEL
secflash-0.1.2.dist-info/top_level.txt
secflash-0.1.2.dist-info/RECORD
