Metadata-Version: 2.4
Name: secflash
Version: 0.1.2
Summary: A vulnerability scanning and reporting library based on NVD data
Home-page: https://github.com/NeoScout-tech/SecFlash
Author: saikonohack
Author-email: saintklovus@gmail.com
Classifier: Programming Language :: Python :: 3
Classifier: License :: OSI Approved :: MIT License
Classifier: Operating System :: OS Independent
Requires-Python: >=3.8
Requires-Dist: nvdlib>=0.7.6
Requires-Dist: reportlab>=3.6.13
Requires-Dist: requests>=2.31.0
Requires-Dist: packaging>=25.0
Requires-Dist: colorlog>=6.9.0
Dynamic: author
Dynamic: author-email
Dynamic: classifier
Dynamic: description
Dynamic: description-content-type
Dynamic: home-page
Dynamic: requires-dist
Dynamic: requires-python
Dynamic: summary
